merlinpy/__init__.py
merlinpy/experiment.py
merlinpy/fft.py
merlinpy/utils.py
merlinpy/datapipeline/__init__.py
merlinpy/datapipeline/data.py
merlinpy/datapipeline/patching.py
merlinpy/datapipeline/utils_data.py
merlinpy/datapipeline/sampling/__init__.py
merlinpy/datapipeline/sampling/sampling.py
merlinpy/datapipeline/sampling/VISTA/__init__.py
merlinpy/datapipeline/sampling/VISTA/dispdup.py
merlinpy/datapipeline/sampling/VISTA/fillK.py
merlinpy/datapipeline/sampling/VISTA/main.py
merlinpy/datapipeline/sampling/VISTA/randp.py
merlinpy/fastmri/__init__.py
merlinpy/fastmri/data.py
merlinpy/fastmri/utils.py
merlinpy/losses/__init__.py
merlinpy/losses/pairwise_loss.py
merlinpy/recon/BART.py
merlinpy/recon/__init__.py
merlinpy/recon/iterativeSENSE.py
merlinpy/test/__init__.py
merlinpy/test/test_datapipeline_patching.py
merlinpy/test/test_datapipeline_sampling.py
merlinpy/test/test_recon_BART.py
merlinpy/test/test_recon_iterativeSENSE.py
merlinpy/wandb/__init__.py
merlinpy/wandb/utils.py
merlinpy_mri-0.4.0.dist-info/METADATA
merlinpy_mri-0.4.0.dist-info/WHEEL
merlinpy_mri-0.4.0.dist-info/top_level.txt
merlinpy_mri-0.4.0.dist-info/RECORD
