Metadata-Version: 2.1
Name: merlinpy-mri
Version: 0.4.0
Summary: Machine Enhanced Reconstruction Learning and Interpretation Networks (MERLIN) - merlinpy
Home-page: https://github.com/midas-tum/merlin
Author: Kerstin Hammernik, Thomas Kuestner
Author-email: merlin.midastum@gmail.com
License: MIT
Platform: UNKNOWN
Classifier: Programming Language :: Python :: 3 :: Only
Classifier: Programming Language :: C++
Classifier: License :: OSI Approved :: MIT License
Classifier: Operating System :: OS Independent
Classifier: Topic :: Scientific/Engineering :: Artificial Intelligence
Classifier: Topic :: Scientific/Engineering :: Medical Science Apps.
Requires-Dist: numpy (>=1.15)
Requires-Dist: xmltodict
Requires-Dist: pyyaml
Requires-Dist: pandas
Requires-Dist: tqdm
Requires-Dist: scipy
Requires-Dist: scikit-image
Requires-Dist: matplotlib
Requires-Dist: joblib
Requires-Dist: sphinx
Requires-Dist: sphinxjp.themes.basicstrap
Requires-Dist: sphinx-rtd-theme
Requires-Dist: breathe
